mroll/__init__.py
mroll/commands.py
mroll/config.py
mroll/databases/__init__.py
mroll/databases/monetdb.py
mroll/exceptions.py
mroll/migration.py
mroll/templates/env.py
mroll/templates/mroll.ini
mroll/templates/revision_template.txt
mroll-0.4.0.dist-info/entry_points.txt
mroll-0.4.0.dist-info/LICENSE
mroll-0.4.0.dist-info/WHEEL
mroll-0.4.0.dist-info/METADATA
mroll-0.4.0.dist-info/RECORD
