Metadata-Version: 2.1
Name: mroll
Version: 0.4.0
Summary: monetdb migration tool
Home-page: https://github.com/MonetDBSolutions/mroll
License: MPL-2.0
Keywords: migration,monetdb,mroll
Author: svetlin
Author-email: svetlin.stalinov@monetdbsolutions.com
Requires-Python: >=3.7,<4.0
Classifier: License :: OSI Approved
Classifier: License :: OSI Approved :: Mozilla Public License 2.0 (MPL 2.0)
Classifier: Programming Language :: Python :: 3
Classifier: Programming Language :: Python :: 3.7
Classifier: Programming Language :: Python :: 3.8
Classifier: Programming Language :: Python :: 3.9
Classifier: Programming Language :: Python :: 3.10
Classifier: Programming Language :: Python :: 3.11
Classifier: Programming Language :: Python :: 3
Classifier: Programming Language :: Python :: 3 :: Only
Classifier: Topic :: Database
Requires-Dist: click (>=8.0.3,<9.0.0)
Requires-Dist: pymonetdb (>=1.3.1,<2.0.0)
Requires-Dist: sqlparse (>=0.3.1,<0.4.0)
Project-URL: Repository, https://github.com/MonetDBSolutions/mroll
